{
  "name": "sub get severa proposals",
  "nodes": [
    {
      "parameters": {
        "inputSource": "passthrough"
      },
      "type": "n8n-nodes-base.executeWorkflowTrigger",
      "typeVersion": 1.1,
      "position": [
        -144,
        -64
      ],
      "id": "e060978b-7602-4845-9713-5d44f10b42c7",
      "name": "When Executed by Another Workflow"
    },
    {
      "parameters": {
        "assignments": {
          "assignments": [
            {
              "id": "cred-client-id",
              "name": "client_id",
              "value": "XXX",
              "type": "string"
            },
            {
              "id": "cred-client-secret",
              "name": "client_secret",
              "value": "XXX",
              "type": "string"
            }
          ]
        },
        "options": {}
      },
      "id": "cf9ad4fc-b14a-4aa5-93ef-69089225a6e2",
      "name": "Severa credentials",
      "type": "n8n-nodes-base.set",
      "typeVersion": 3.4,
      "position": [
        80,
        -64
      ],
      "notesInFlow": true,
      "notes": "Set your Severa REST API Client ID and Client Secret here (from Severa UI → Rest Api settings). Replace YOUR_CLIENT_ID and YOUR_CLIENT_SECRET with your values."
    },
    {
      "parameters": {
        "jsCode": "// Get access token from Severa API using client_credentials grant.\n// No refresh token needed: this is the initial token request.\n// Reads client_id and client_secret from the previous \"Severa credentials\" (Edit Fields) node.\n\nconst SEVERA_BASE = 'https://api.severa.visma.com/rest-api';\nconst inputItem = $input.first();\nconst clientId = inputItem.json.client_id;\nconst clientSecret = inputItem.json.client_secret;\n\nif (!clientId || !clientSecret) {\n  throw new Error(\n    'Missing client_id or client_secret. Set them in the \"Severa credentials\" Edit Fields node.'\n  );\n}\n\nconst tokenUrl = `${SEVERA_BASE}/v1/login/oauth/token`;\nconst body = {\n  grant_type: 'client_credentials',\n  client_id: clientId,\n  client_secret: clientSecret,\n  scope: 'projects:read',\n};\n\nconst response = await this.helpers.httpRequest({\n  method: 'POST',\n  url: tokenUrl,\n  body,\n  json: true,\n});\n\nif (!response.access_token) {\n  throw new Error(\n    'Token response did not contain access_token. Check client_id and client_secret in the Severa credentials node.'\n  );\n}\n\n// Pass through credentials and add token (and refresh_token if API returned one).\nreturn [\n  {\n    json: {\n      ...inputItem.json,\n      access_token: response.access_token,\n      refresh_token: response.refresh_token || null,\n      expires_in: response.expires_in,\n      token_type: response.token_type || 'Bearer',\n    },\n  },\n];\n"
      },
      "id": "166bc81d-02c9-4555-978b-7d714267601d",
      "name": "Get Severa Access Token",
      "type": "n8n-nodes-base.code",
      "typeVersion": 2,
      "position": [
        304,
        -64
      ],
      "notesInFlow": true,
      "notes": "POST /v1/login/oauth/token with client_credentials. Uses client_id and client_secret from previous node. Outputs access_token (and refresh_token if API returns it)."
    },
    {
      "parameters": {
        "jsCode": "// Pull all proposals from Severa API (all pages).\n// Uses access_token from the previous \"Get Severa Access Token\" node.\n// Paginates automatically (rowCount=100, NextPageToken).\n\nconst SEVERA_BASE = 'https://api.severa.visma.com/rest-api';\nconst ROW_COUNT = 100;\n\nconst inputItem = $input.first();\nconst accessToken = inputItem.json.access_token;\n\nif (!accessToken) {\n  throw new Error('No access_token in input. Run \"Get Severa Access Token\" first.');\n}\n\nconst headers = {\n  Authorization: `Bearer ${accessToken}`,\n  Accept: 'application/json',\n};\n\nlet allProposals = [];\nlet pageToken = null;\n\ndo {\n  let url = `${SEVERA_BASE}/v1/proposals?rowCount=${ROW_COUNT}`;\n  if (pageToken) {\n    url += '&pageToken=' + encodeURIComponent(pageToken);\n  }\n\n  let response;\n  try {\n    response = await this.helpers.httpRequest({\n      method: 'GET',\n      url: url,\n      headers,\n      json: true,\n      returnFullResponse: true,\n    });\n  } catch (err) {\n    if (err.response && err.response.status === 403) {\n      const data = err.response.data;\n      const msg = (data && (data.message || data.error_description || (typeof data === 'string' ? data : JSON.stringify(data)))) || err.message;\n      throw new Error('Severa API 403 Forbidden. Ensure your REST API client has projects:read (Proposals) permission in Severa Rest Api settings. ' + msg);\n    }\n    throw err;\n  }\n\n  const page = Array.isArray(response.body) ? response.body : [];\n  allProposals = allProposals.concat(page);\n\n  const h = response.headers || {};\n  pageToken = h.nextpagetoken || h.NextPageToken || null;\n} while (pageToken);\n\nreturn allProposals.map((p) => ({ json: p }));\n"
      },
      "id": "caf1c0af-9f54-4974-9fb7-1dc038e0cae6",
      "name": "Get Active Proposals1",
      "type": "n8n-nodes-base.code",
      "typeVersion": 2,
      "position": [
        528,
        -64
      ],
      "notesInFlow": true,
      "notes": "GET /v1/proposals with pagination. Returns all proposals (no status filter)."
    }
  ],
  "pinData": {},
  "connections": {
    "Severa credentials": {
      "main": [
        [
          {
            "node": "Get Severa Access Token",
            "type": "main",
            "index": 0
          }
        ]
      ]
    },
    "Get Severa Access Token": {
      "main": [
        [
          {
            "node": "Get Active Proposals1",
            "type": "main",
            "index": 0
          }
        ]
      ]
    },
    "When Executed by Another Workflow": {
      "main": [
        [
          {
            "node": "Severa credentials",
            "type": "main",
            "index": 0
          }
        ]
      ]
    }
  },
  "active": true,
  "settings": {
    "executionOrder": "v1",
    "binaryMode": "separate",
    "availableInMCP": false
  },
  "versionId": "118db20e-7c30-4d1b-853e-9ed0537fccbc",
  "meta": {
    "instanceId": "db255330f3ec3db546b124f8dda741868a807ba82675464b4eb251e1ee96ed02"
  },
  "id": "5Tb3KNEKc3eD8IJs",
  "tags": [
    {
      "updatedAt": "2026-02-23T10:45:08.199Z",
      "createdAt": "2026-02-23T10:45:08.199Z",
      "id": "T5GGgIFcBuHl9RTM",
      "name": "severa"
    }
  ]
}